brewblox_ctl/__init__.py
brewblox_ctl/__main__.py
brewblox_ctl/click_helpers.py
brewblox_ctl/commands/__init__.py
brewblox_ctl/commands/docker.py
brewblox_ctl/commands/env.py
brewblox_ctl/commands/http.py
brewblox_ctl/commands/install.py
brewblox_ctl/commands/snapshot.py
brewblox_ctl/const.py
brewblox_ctl/testing.py
brewblox_ctl/utils.py
brewblox_ctl-0.27.0.dist-info/entry_points.txt
brewblox_ctl-0.27.0.dist-info/LICENSE
brewblox_ctl-0.27.0.dist-info/WHEEL
brewblox_ctl-0.27.0.dist-info/METADATA
brewblox_ctl-0.27.0.dist-info/RECORD
