Metadata-Version: 2.1
Name: brewblox-ctl
Version: 0.27.0
Summary: Brewblox management tool
License: GPL-3.0
Author: BrewPi
Author-email: development@brewpi.com
Requires-Python: >=3.6,<4
Classifier: License :: OSI Approved :: GNU General Public License v3 (GPLv3)
Classifier: Programming Language :: Python :: 3
Classifier: Programming Language :: Python :: 3.6
Classifier: Programming Language :: Python :: 3.7
Classifier: Programming Language :: Python :: 3.8
Classifier: Programming Language :: Python :: 3.9
Requires-Dist: PyYAML (>=5.4.1,<6.0.0)
Requires-Dist: click (>=7)
Requires-Dist: configobj (>=5.0.6,<6.0.0)
Requires-Dist: docker (>=5.0.0,<6.0.0)
Requires-Dist: docker-compose (>=1.29.2,<2.0.0)
Requires-Dist: pyserial (>=3)
Requires-Dist: python-dotenv[cli] (>=0.19.0,<0.20.0)
Requires-Dist: pyusb (>=1.2)
Requires-Dist: requests (>=2.26.0,<3.0.0)
Requires-Dist: zeroconf (>=0.33.1,<0.34.0)
